GISL/__init__.py
GISL/gisl.py
GISL/gisl_libinfo.py
GISL-1.0.1.dist-info/LICENSE
GISL-1.0.1.dist-info/METADATA
GISL-1.0.1.dist-info/WHEEL
GISL-1.0.1.dist-info/top_level.txt
GISL-1.0.1.dist-info/RECORD
