Metadata-Version: 2.1
Name: GISL
Version: 1.0.1
Summary: GISL is a versatile Python library designed for Geographic Information System (GIS) tasks. It offers methods to retrieve country names and codes, determine continents, geocode IP addresses, calculate distances between coordinates, find time zones, and get addresses from latitude and longitude. GISL also allows users to obtain the public IP address of the current machine, making it an essential toolkit for developers and researchers working with geospatial data.
Author: Theo Nilsson
Author-email: theonilsson2012@icloud.com
Keywords: python,geography,geocoding,timezone,timezones,location
Classifier: Development Status :: 1 - Planning
Classifier: Intended Audience :: Developers
Classifier: Programming Language :: Python :: 3
Classifier: Operating System :: Unix
Classifier: Operating System :: MacOS :: MacOS X
Classifier: Operating System :: Microsoft :: Windows
License-File: LICENSE
Requires-Dist: geopy
Requires-Dist: geocoder
Requires-Dist: pycountry
Requires-Dist: pycountry-convert
Requires-Dist: requests
Requires-Dist: timezonefinder
